sherlock/__init__.py
sherlock/cli.py
sherlock/scanner.py
sherlock_scanner-1.0.1.dist-info/METADATA
sherlock_scanner-1.0.1.dist-info/WHEEL
sherlock_scanner-1.0.1.dist-info/entry_points.txt
sherlock_scanner-1.0.1.dist-info/top_level.txt
sherlock_scanner-1.0.1.dist-info/RECORD
