Metadata-Version: 2.2
Name: sherlock-scanner
Version: 1.0.1
Summary: A Python security scanner for hardcoded secrets and API keys.
Author: Omeriko
Author-email: your.email@example.com
Classifier: Programming Language :: Python :: 3
Classifier: License :: OSI Approved :: MIT License
Requires-Python: >=3.6
Requires-Dist: click
Dynamic: author
Dynamic: author-email
Dynamic: classifier
Dynamic: description
Dynamic: description-content-type
Dynamic: requires-dist
Dynamic: requires-python
Dynamic: summary
